setup.py
comet/__init__.py
comet/config.py
comet/csvio.py
comet/data.py
comet/main.py
comet/plot.py
comet/time.py
comet_sensor.egg-info/PKG-INFO
comet_sensor.egg-info/SOURCES.txt
comet_sensor.egg-info/dependency_links.txt
comet_sensor.egg-info/entry_points.txt
comet_sensor.egg-info/requires.txt
comet_sensor.egg-info/top_level.txt