Metadata-Version: 1.0
Name: comet-sensor
Version: 0.7.2.1
Summary: A simple tool for retreiving and dealing with climate data from the Comet T6540 Climate sensor.
Home-page: UNKNOWN
Author: Rovanion Luckey
Author-email: rovanion.luckey@gmail.com
License: GPL3
Platform: UNKNOWN
